<annotation verified="yes">
	<folder>images</folder>
	<filename>091.jpg</filename>
	<path>E:\Projects\Coding\russian-license-plate-recognition\workspace\dataset\images\091.jpg</path>
	<source>
		<database>Unknown</database>
	</source>
	<size>
		<width>1600</width>
		<height>1200</height>
		<depth>3</depth>
	</size>
	<segmented>0</segmented>
	<object>
		<name>car</name>
		<pose>Unspecified</pose>
		<truncated>0</truncated>
		<difficult>0</difficult>
		<bndbox>
			<xmin>575</xmin>
			<ymin>353</ymin>
			<xmax>1531</xmax>
			<ymax>915</ymax>
		</bndbox>
	</object>
	<object>
		<name>plate</name>
		<pose>Unspecified</pose>
		<truncated>0</truncated>
		<difficult>0</difficult>
		<bndbox>
			<xmin>1195</xmin>
			<ymin>632</ymin>
			<xmax>1481</xmax>
			<ymax>779</ymax>
		</bndbox>
	</object>
</annotation>
