<annotation>
	<folder>data</folder>
	<filename>189.jpg</filename>
	<path>E:\Projects\Coding\russian-license-plate-recognition\data\189.jpg</path>
	<source>
		<database>Unknown</database>
	</source>
	<size>
		<width>680</width>
		<height>546</height>
		<depth>3</depth>
	</size>
	<segmented>0</segmented>
	<object>
		<name>car_rear</name>
		<pose>Unspecified</pose>
		<truncated>0</truncated>
		<difficult>0</difficult>
		<bndbox>
			<xmin>49</xmin>
			<ymin>164</ymin>
			<xmax>653</xmax>
			<ymax>475</ymax>
		</bndbox>
	</object>
	<object>
		<name>plate</name>
		<pose>Unspecified</pose>
		<truncated>0</truncated>
		<difficult>0</difficult>
		<bndbox>
			<xmin>237</xmin>
			<ymin>219</ymin>
			<xmax>450</xmax>
			<ymax>269</ymax>
		</bndbox>
	</object>
</annotation>
