<annotation>
	<folder>data</folder>
	<filename>185.jpg</filename>
	<path>E:\Projects\Coding\russian-license-plate-recognition\data\185.jpg</path>
	<source>
		<database>Unknown</database>
	</source>
	<size>
		<width>604</width>
		<height>453</height>
		<depth>3</depth>
	</size>
	<segmented>0</segmented>
	<object>
		<name>car_rear</name>
		<pose>Unspecified</pose>
		<truncated>0</truncated>
		<difficult>0</difficult>
		<bndbox>
			<xmin>83</xmin>
			<ymin>173</ymin>
			<xmax>516</xmax>
			<ymax>374</ymax>
		</bndbox>
	</object>
	<object>
		<name>car_rear</name>
		<pose>Unspecified</pose>
		<truncated>0</truncated>
		<difficult>0</difficult>
		<bndbox>
			<xmin>219</xmin>
			<ymin>228</ymin>
			<xmax>374</xmax>
			<ymax>261</ymax>
		</bndbox>
	</object>
</annotation>
