<annotation verified="yes">
	<folder>images</folder>
	<filename>001.jpg</filename>
	<path>E:\Projects\Coding\russian-license-plate-recognition\workspace\dataset\images\001.jpg</path>
	<source>
		<database>Unknown</database>
	</source>
	<size>
		<width>1200</width>
		<height>900</height>
		<depth>3</depth>
	</size>
	<segmented>0</segmented>
	<object>
		<name>car</name>
		<pose>Unspecified</pose>
		<truncated>0</truncated>
		<difficult>0</difficult>
		<bndbox>
			<xmin>190</xmin>
			<ymin>459</ymin>
			<xmax>934</xmax>
			<ymax>727</ymax>
		</bndbox>
	</object>
	<object>
		<name>plate</name>
		<pose>Unspecified</pose>
		<truncated>0</truncated>
		<difficult>0</difficult>
		<bndbox>
			<xmin>421</xmin>
			<ymin>620</ymin>
			<xmax>717</xmax>
			<ymax>683</ymax>
		</bndbox>
	</object>
</annotation>
